pydantic2zod/__init__.py
pydantic2zod/__main__.py
pydantic2zod/_codegen.py
pydantic2zod/_compiler.py
pydantic2zod/_parser.py
pydantic2zod/model.py
pydantic2zod-0.1.1.dist-info/LICENSE
pydantic2zod-0.1.1.dist-info/METADATA
pydantic2zod-0.1.1.dist-info/WHEEL
pydantic2zod-0.1.1.dist-info/RECORD
