Metadata-Version: 2.1
Name: pydantic2zod
Version: 0.1.1
Summary: Pydantic to zod declaration compiler.
Home-page: https://github.com/argyle-engineering/pydantic2zod
License: MIT
Author: Povilas Balciunas
Author-email: povilas@argyle.com
Requires-Python: >=3.10,<4.0
Classifier: License :: OSI Approved :: MIT License
Classifier: Programming Language :: Python :: 3
Classifier: Programming Language :: Python :: 3.10
Classifier: Programming Language :: Python :: 3.11
Classifier: Programming Language :: Python :: 3.12
Classifier: Programming Language :: Python :: 3.13
Requires-Dist: libcst (>=0.4,<2)
Requires-Dist: networkx (>=2,<4)
Requires-Dist: typer (>=0.7.0)
Requires-Dist: typing-extensions (>=4,<5)
Project-URL: Documentation, https://github.com/argyle-engineering/pydantic2zod
Project-URL: Repository, https://github.com/argyle-engineering/pydantic2zod
